MANIFEST.in
setup.py
remembeep/__init__.py
remembeep/default.mp3
remembeep.egg-info/PKG-INFO
remembeep.egg-info/SOURCES.txt
remembeep.egg-info/dependency_links.txt
remembeep.egg-info/entry_points.txt
remembeep.egg-info/requires.txt
remembeep.egg-info/top_level.txt