Metadata-Version: 1.1
Name: remembeep
Version: 1.6
Summary: Simple script for plaing mp3 file periodically
Home-page: https://github.com/imbolc/remembeep
Author: Imbolc
Author-email: imbolc@imbolc.name
License: ISC
Platform: UNKNOWN
Classifier: Development Status :: 4 - Beta
Classifier: Intended Audience :: Developers
Classifier: License :: OSI Approved :: ISC License (ISCL)
Classifier: Programming Language :: Python
